gedi_canopy_height/__init__.py
gedi_canopy_height/download.py
gedi_canopy_height/gedi_canopy_height.py
gedi_canopy_height/version.txt
gedi_canopy_height-1.2.1.dist-info/licenses/LICENSE
gedi_canopy_height-1.2.1.dist-info/METADATA
gedi_canopy_height-1.2.1.dist-info/WHEEL
gedi_canopy_height-1.2.1.dist-info/top_level.txt
gedi_canopy_height-1.2.1.dist-info/RECORD
